validate/__init__.py
validate/karaushev3d.py
drt_validate-0.0.2.dist-info/LICENSE
drt_validate-0.0.2.dist-info/METADATA
drt_validate-0.0.2.dist-info/WHEEL
drt_validate-0.0.2.dist-info/top_level.txt
drt_validate-0.0.2.dist-info/RECORD
